MRzeroCore/__init__.py
MRzeroCore/_prepass.abi3.so
MRzeroCore/phantom/brainweb/.gitignore
MRzeroCore/phantom/brainweb/__init__.py
MRzeroCore/phantom/brainweb/brainweb_data.json
MRzeroCore/phantom/brainweb/brainweb_data_sources.txt
MRzeroCore/phantom/brainweb/output/.gitkeep
MRzeroCore/phantom/custom_voxel_phantom.py
MRzeroCore/phantom/nifti_phantom.py
MRzeroCore/phantom/sim_data.py
MRzeroCore/phantom/tissue_dict.py
MRzeroCore/phantom/voxel_grid_phantom.py
MRzeroCore/pulseq/exporter.py
MRzeroCore/pulseq/exporter_v2.py
MRzeroCore/pulseq/helpers.py
MRzeroCore/pulseq/pulseq_exporter.py
MRzeroCore/pulseq/pulseq_loader/__init__.py
MRzeroCore/pulseq/pulseq_loader/adc.py
MRzeroCore/pulseq/pulseq_loader/helpers.py
MRzeroCore/pulseq/pulseq_loader/pulse.py
MRzeroCore/pulseq/pulseq_loader/pulseq_file/__init__.py
MRzeroCore/pulseq/pulseq_loader/pulseq_file/adc.py
MRzeroCore/pulseq/pulseq_loader/pulseq_file/block.py
MRzeroCore/pulseq/pulseq_loader/pulseq_file/definitons.py
MRzeroCore/pulseq/pulseq_loader/pulseq_file/gradient.py
MRzeroCore/pulseq/pulseq_loader/pulseq_file/helpers.py
MRzeroCore/pulseq/pulseq_loader/pulseq_file/rf.py
MRzeroCore/pulseq/pulseq_loader/pulseq_file/trap.py
MRzeroCore/pulseq/pulseq_loader/spoiler.py
MRzeroCore/reconstruction.py
MRzeroCore/sequence.py
MRzeroCore/simulation/isochromat_sim.py
MRzeroCore/simulation/main_pass.py
MRzeroCore/simulation/pre_pass.py
MRzeroCore/simulation/sig_to_mrd.py
MRzeroCore/util.py
MRzeroCore.libs/libgcc_s-262c4f60.so.1
mrzerocore-0.4.3.dist-info/METADATA
mrzerocore-0.4.3.dist-info/WHEEL
mrzerocore-0.4.3.dist-info/licenses/LICENSE
mrzerocore-0.4.3.dist-info/RECORD
