Metadata-Version: 2.4
Name: mrzerocore
Version: 0.4.3
Classifier: Programming Language :: Rust
Classifier: Programming Language :: Python :: Implementation :: CPython
Classifier: Programming Language :: Python :: Implementation :: PyPy
Classifier: License :: OSI Approved :: GNU Affero General Public License v3
Requires-Dist: ismrmrd
Requires-Dist: matplotlib>=3.5
Requires-Dist: pydisseqt>=0.1.13
Requires-Dist: pypulseq
Requires-Dist: requests>=2.20
Requires-Dist: scikit-image
Requires-Dist: scipy>=1.7
Requires-Dist: torchkbnufft
Requires-Dist: torch>=1.12
Requires-Dist: tqdm
Requires-Dist: nibabel
License-File: LICENSE
Summary: Core functionality of MRzero
Author-email: Jonathan Endres <jonathan.endres@uk-erlangen.de>
Requires-Python: >=3.9
Project-URL: Documentation, https://mrsources.github.io/MRzero-Core/
Project-URL: MRzero-Paper, https://arxiv.org/abs/2002.04265
Project-URL: Repository, https://github.com/MRsources/MRzero-Core
